briefnewscli/__init__.py
briefnewscli/api.py
briefnewscli/cli.py
briefnewscli/config.py
briefnewscli/summarizer.py
briefnewscli/utils.py
briefnewscli-0.2.0.dist-info/LICENSE
briefnewscli-0.2.0.dist-info/METADATA
briefnewscli-0.2.0.dist-info/WHEEL
briefnewscli-0.2.0.dist-info/entry_points.txt
briefnewscli-0.2.0.dist-info/top_level.txt
briefnewscli-0.2.0.dist-info/RECORD
