Metadata-Version: 2.1
Name: briefnewscli
Version: 0.2.0
Summary: A Python CLI for fetching and summarizing news from the New York Times.
Home-page: UNKNOWN
Author: PlatformPM
Author-email: diego.penuela@gmail.com
License: Creative Commons Legal Code
Platform: UNKNOWN
License-File: LICENSE
Requires-Dist: typer
Requires-Dist: python-decouple
Requires-Dist: requests
Requires-Dist: torch
Requires-Dist: transformers
